odoo/addons/web_widget_image_download/README.rst
odoo/addons/web_widget_image_download/__init__.py
odoo/addons/web_widget_image_download/__manifest__.py
odoo/addons/web_widget_image_download/i18n/ca.po
odoo/addons/web_widget_image_download/i18n/es.po
odoo/addons/web_widget_image_download/i18n/hr.po
odoo/addons/web_widget_image_download/i18n/lt.po
odoo/addons/web_widget_image_download/i18n/nl_NL.po
odoo/addons/web_widget_image_download/i18n/pt.po
odoo/addons/web_widget_image_download/i18n/pt_BR.po
odoo/addons/web_widget_image_download/i18n/tr.po
odoo/addons/web_widget_image_download/i18n/web_widget_image_download.pot
odoo/addons/web_widget_image_download/i18n/zh_CN.po
odoo/addons/web_widget_image_download/readme/CONTRIBUTORS.rst
odoo/addons/web_widget_image_download/readme/DESCRIPTION.rst
odoo/addons/web_widget_image_download/readme/USAGE.rst
odoo/addons/web_widget_image_download/static/description/icon.png
odoo/addons/web_widget_image_download/static/description/index.html
odoo/addons/web_widget_image_download/static/src/js/web_widget_image_download.js
odoo/addons/web_widget_image_download/static/src/scss/web_widget_image_download.scss
odoo/addons/web_widget_image_download/static/src/xml/web_widget_image_download.xml
odoo/addons/web_widget_image_download/views/assets.xml
odoo12_addon_web_widget_image_download-12.0.1.0.0.99.dev19.dist-info/METADATA
odoo12_addon_web_widget_image_download-12.0.1.0.0.99.dev19.dist-info/WHEEL
odoo12_addon_web_widget_image_download-12.0.1.0.0.99.dev19.dist-info/top_level.txt
odoo12_addon_web_widget_image_download-12.0.1.0.0.99.dev19.dist-info/RECORD
